Strings table:
Entry 0 -- "Excelente!"
Entry 1 -- "Aprovado com bom desempenho."
Entry 2 -- "Recuperação."
Entry 3 -- "Reprovado."
Entry 4 -- "Nota inválida. Digite um valor entre 0 e 10."


Global symbol table:
Entry 0 -- name: nota, kind: VARIABLE, line: 4, type: real


digraph {
graph [ordering="out"];
node0[label="program"];
node1[label="var_list"];
node2[label="(real) nota@"];
node1 -> node2;
node0 -> node1;
node3[label="block"];
node4[label="(real) :="];
node5[label="(real) nota@"];
node4 -> node5;
node6[label="(real) I2R"];
node7[label="(integer)  6"];
node6 -> node7;
node4 -> node6;
node3 -> node4;
node8[label="if"];
node9[label="(boolean) and"];
node10[label="(boolean) >="];
node11[label="(real) nota@"];
node10 -> node11;
node12[label="(integer)  0"];
node10 -> node12;
node9 -> node10;
node13[label="(boolean) <="];
node14[label="(real) nota@"];
node13 -> node14;
node15[label="(integer)  10"];
node13 -> node15;
node9 -> node13;
node8 -> node9;
node16[label="structure_stmt"];
node17[label="if"];
node18[label="(boolean) >="];
node19[label="(real) nota@"];
node18 -> node19;
node20[label="(integer)  7"];
node18 -> node20;
node17 -> node18;
node21[label="structure_stmt"];
node22[label="if"];
node23[label="(boolean) >="];
node24[label="(real) nota@"];
node23 -> node24;
node25[label="(integer)  9"];
node23 -> node25;
node22 -> node23;
node26[label="write"];
node27[label="(string)  \"Excelente!\""];
node26 -> node27;
node22 -> node26;
node28[label="write"];
node29[label="(string)  \"Aprovado com bom desempenho.\""];
node28 -> node29;
node22 -> node28;
node21 -> node22;
node17 -> node21;
node30[label="structure_stmt"];
node31[label="if"];
node32[label="(boolean) >="];
node33[label="(real) nota@"];
node32 -> node33;
node34[label="(integer)  5"];
node32 -> node34;
node31 -> node32;
node35[label="write"];
node36[label="(string)  \"Recuperação.\""];
node35 -> node36;
node31 -> node35;
node37[label="write"];
node38[label="(string)  \"Reprovado.\""];
node37 -> node38;
node31 -> node37;
node30 -> node31;
node17 -> node30;
node16 -> node17;
node8 -> node16;
node39[label="write"];
node40[label="(string)  \"Nota inválida. Digite um valor entre 0 e 10.\""];
node39 -> node40;
node8 -> node39;
node3 -> node8;
node0 -> node3;
}

=== EXECUTANDO O PROGRAMA ===

Recuperação.

=== GERANDO CÓDIGO JASMIN ===

Código Jasmin gerado com sucesso em: ../tests/in/valid_15.j

=== CÓDIGO JASMIN GERADO ===

.class public PascalProgram
.super java/lang/Object

.method public <init>()V
  aload_0
  invokespecial java/lang/Object/<init>()V
  return
.end method

.method public static main([Ljava/lang/String;)V
  .limit stack 10
  .limit locals 10
  fconst_0
  fstore 0
  bipush 6
  i2f
  fstore 0
  fload 0
  iconst_0
  if_icmpge L0
  iconst_0
  goto L1
L0:
  iconst_1
L1:
  fload 0
  bipush 10
  if_icmple L2
  iconst_0
  goto L3
L2:
  iconst_1
L3:
  iand
  ifeq L4
  fload 0
  bipush 7
  if_icmpge L6
  iconst_0
  goto L7
L6:
  iconst_1
L7:
  ifeq L8
  fload 0
  bipush 9
  if_icmpge L10
  iconst_0
  goto L11
L10:
  iconst_1
L11:
  ifeq L12
  getstatic java/lang/System/out Ljava/io/PrintStream;
  ldc "Excelente!"
  invokevirtual java/io/PrintStream/println(Ljava/lang/String;)V
  goto L13
L12:
  getstatic java/lang/System/out Ljava/io/PrintStream;
  ldc "Aprovado com bom desempenho."
  invokevirtual java/io/PrintStream/println(Ljava/lang/String;)V
L13:
  goto L9
L8:
  fload 0
  iconst_5
  if_icmpge L14
  iconst_0
  goto L15
L14:
  iconst_1
L15:
  ifeq L16
  getstatic java/lang/System/out Ljava/io/PrintStream;
  ldc "Recuperação."
  invokevirtual java/io/PrintStream/println(Ljava/lang/String;)V
  goto L17
L16:
  getstatic java/lang/System/out Ljava/io/PrintStream;
  ldc "Reprovado."
  invokevirtual java/io/PrintStream/println(Ljava/lang/String;)V
L17:
L9:
  goto L5
L4:
  getstatic java/lang/System/out Ljava/io/PrintStream;
  ldc "Nota inválida. Digite um valor entre 0 e 10."
  invokevirtual java/io/PrintStream/println(Ljava/lang/String;)V
L5:
  return
.end method

