Strings table:
Entry 0 -- "O numero "
Entry 1 -- " é False."
Entry 2 -- " é impar."


Global symbol table:
Entry 0 -- name: numero, kind: VARIABLE, line: 4, type: boolean
Entry 1 -- name: numero2, kind: VARIABLE, line: 5, type: real


digraph {
graph [ordering="out"];
node0[label="program"];
node1[label="var_list"];
node2[label="(boolean) numero@"];
node1 -> node2;
node3[label="(real) numero2@"];
node1 -> node3;
node0 -> node1;
node4[label="block"];
node5[label="(boolean) :="];
node6[label="(boolean) numero@"];
node5 -> node6;
node7[label="(boolean)  true"];
node5 -> node7;
node4 -> node5;
node8[label="(real) :="];
node9[label="(real) numero2@"];
node8 -> node9;
node10[label="(real) I2R"];
node11[label="(integer)  2"];
node10 -> node11;
node8 -> node10;
node4 -> node8;
node12[label="if"];
node13[label="(boolean) ="];
node14[label="(boolean)  false"];
node13 -> node14;
node15[label="(boolean) numero@"];
node13 -> node15;
node12 -> node13;
node16[label="write"];
node17[label="(string)  \"O numero \""];
node16 -> node17;
node18[label="(string) B2S"];
node19[label="(boolean) numero@"];
node18 -> node19;
node16 -> node18;
node20[label="(string)  \" é False.\""];
node16 -> node20;
node12 -> node16;
node21[label="write"];
node22[label="(string)  \"O numero \""];
node21 -> node22;
node23[label="(string) B2S"];
node24[label="(boolean) numero@"];
node23 -> node24;
node21 -> node23;
node25[label="(string)  \" é impar.\""];
node21 -> node25;
node12 -> node21;
node4 -> node12;
node0 -> node4;
}

=== EXECUTANDO O PROGRAMA ===

O numero  true  é impar.

=== GERANDO CÓDIGO JASMIN ===

Código Jasmin gerado com sucesso em: ../tests/in/valid_07.j

=== CÓDIGO JASMIN GERADO ===

.class public PascalProgram
.super java/lang/Object

.method public <init>()V
  aload_0
  invokespecial java/lang/Object/<init>()V
  return
.end method

.method public static main([Ljava/lang/String;)V
  .limit stack 10
  .limit locals 10
  fconst_0
  fstore 1
  iconst_0
  istore 0
  iconst_1
  istore 0
  iconst_2
  i2f
  fstore 1
  iconst_0
  iload 0
  if_icmpne L0
  iconst_1
  goto L1
L0:
  iconst_0
L1:
  ifeq L2
  getstatic java/lang/System/out Ljava/io/PrintStream;
  ldc "O numero "
  invokevirtual java/io/PrintStream/println(Ljava/lang/String;)V
  getstatic java/lang/System/out Ljava/io/PrintStream;
  iload 0
  invokestatic java/lang/String/valueOf(Z)Ljava/lang/String;
  invokevirtual java/io/PrintStream/println(Ljava/lang/String;)V
  getstatic java/lang/System/out Ljava/io/PrintStream;
  ldc " é False."
  invokevirtual java/io/PrintStream/println(Ljava/lang/String;)V
  goto L3
L2:
  getstatic java/lang/System/out Ljava/io/PrintStream;
  ldc "O numero "
  invokevirtual java/io/PrintStream/println(Ljava/lang/String;)V
  getstatic java/lang/System/out Ljava/io/PrintStream;
  iload 0
  invokestatic java/lang/String/valueOf(Z)Ljava/lang/String;
  invokevirtual java/io/PrintStream/println(Ljava/lang/String;)V
  getstatic java/lang/System/out Ljava/io/PrintStream;
  ldc " é impar."
  invokevirtual java/io/PrintStream/println(Ljava/lang/String;)V
L3:
  return
.end method

