Strings table:
Entry 0 -- "verdadeiro"
Entry 1 -- "falso"


Global symbol table:
Entry 0 -- name: x, kind: VARIABLE, line: 3, type: integer
Entry 1 -- name: y, kind: VARIABLE, line: 3, type: integer
Entry 2 -- name: z, kind: VARIABLE, line: 3, type: integer
Entry 3 -- name: resultado, kind: VARIABLE, line: 4, type: real


digraph {
graph [ordering="out"];
node0[label="program"];
node1[label="var_list"];
node2[label="(integer) x@"];
node1 -> node2;
node3[label="(integer) y@"];
node1 -> node3;
node4[label="(integer) z@"];
node1 -> node4;
node5[label="(real) resultado@"];
node1 -> node5;
node0 -> node1;
node6[label="block"];
node7[label="(integer) :="];
node8[label="(integer) x@"];
node7 -> node8;
node9[label="(integer)  20"];
node7 -> node9;
node6 -> node7;
node10[label="(integer) :="];
node11[label="(integer) y@"];
node10 -> node11;
node12[label="(integer)  3"];
node10 -> node12;
node6 -> node10;
node13[label="(integer) :="];
node14[label="(integer) z@"];
node13 -> node14;
node15[label="(integer) -"];
node16[label="(integer) x@"];
node15 -> node16;
node17[label="(integer) y@"];
node15 -> node17;
node13 -> node15;
node6 -> node13;
node18[label="(real) :="];
node19[label="(real) resultado@"];
node18 -> node19;
node20[label="(real) /"];
node21[label="(integer) x@"];
node20 -> node21;
node22[label="(integer) y@"];
node20 -> node22;
node18 -> node20;
node6 -> node18;
node23[label="write"];
node24[label="(string) I2S"];
node25[label="(integer) z@"];
node24 -> node25;
node23 -> node24;
node6 -> node23;
node26[label="write"];
node27[label="(string) R2S"];
node28[label="(real) resultado@"];
node27 -> node28;
node26 -> node27;
node6 -> node26;
node29[label="if"];
node30[label="(boolean) >"];
node31[label="(integer) x@"];
node30 -> node31;
node32[label="(integer) y@"];
node30 -> node32;
node29 -> node30;
node33[label="write"];
node34[label="(string)  \"verdadeiro\""];
node33 -> node34;
node29 -> node33;
node35[label="write"];
node36[label="(string)  \"falso\""];
node35 -> node36;
node29 -> node35;
node6 -> node29;
node0 -> node6;
}

=== EXECUTANDO O PROGRAMA ===

17
6.6666665
verdadeiro

=== GERANDO CÓDIGO JASMIN ===

Código Jasmin gerado com sucesso em: ../tests/in/valid_09.j

=== CÓDIGO JASMIN GERADO ===

.class public PascalProgram
.super java/lang/Object

.method public <init>()V
  aload_0
  invokespecial java/lang/Object/<init>()V
  return
.end method

.method public static main([Ljava/lang/String;)V
  .limit stack 10
  .limit locals 10
  fconst_0
  fstore 3
  iconst_0
  istore 0
  iconst_0
  istore 1
  iconst_0
  istore 2
  bipush 20
  istore 0
  iconst_3
  istore 1
  iload 0
  iload 1
  isub
  istore 2
  iload 0
  iload 1
  fdiv
  fstore 3
  getstatic java/lang/System/out Ljava/io/PrintStream;
  iload 2
  invokestatic java/lang/String/valueOf(I)Ljava/lang/String;
  invokevirtual java/io/PrintStream/println(Ljava/lang/String;)V
  getstatic java/lang/System/out Ljava/io/PrintStream;
  fload 3
  invokestatic java/lang/String/valueOf(F)Ljava/lang/String;
  invokevirtual java/io/PrintStream/println(Ljava/lang/String;)V
  iload 0
  iload 1
  if_icmpgt L0
  iconst_0
  goto L1
L0:
  iconst_1
L1:
  ifeq L2
  getstatic java/lang/System/out Ljava/io/PrintStream;
  ldc "verdadeiro"
  invokevirtual java/io/PrintStream/println(Ljava/lang/String;)V
  goto L3
L2:
  getstatic java/lang/System/out Ljava/io/PrintStream;
  ldc "falso"
  invokevirtual java/io/PrintStream/println(Ljava/lang/String;)V
L3:
  return
.end method

